[
    {"id":3003,"name":"Axis Bank"},
    {"id":3005,"name":"Bank of Baroda - Retail Banking"},
    {"id":3006,"name":"Bank of India"},
    {"id":3007,"name":"Bank of Maharashtra"},
    {"id":3009,"name":"Canara Bank"},
    {"id":3010,"name":"Catholic Syrian Bank"},
    {"id":3011,"name":"Central Bank of India"},
    {"id":3012,"name":"City Union Bank"},
    {"id":3016,"name":"Deutsche Bank"},
    {"id":3017,"name":"DBS Bank Ltd"},
    {"id":3018,"name":"DCB Bank - Personal"},
    {"id":3019,"name":"Dhanlakshmi Bank"},
    {"id":3020,"name":"Federal Bank"},
    {"id":3021,"name":"HDFC Bank"},
    {"id":3022,"name":"ICICI Bank"},
    {"id":3023,"name":"IDBI Bank"},
    {"id":3024,"name":"IDFC FIRST Bank"},
    {"id":3026,"name":"Indian Bank"},
    {"id":3027,"name":"Indian Overseas Bank"},
    {"id":3028,"name":"IndusInd Bank"},
    {"id":3029,"name":"Jammu and Kashmir Bank"},
    {"id":3030,"name":"Karnataka Bank Ltd"},
    {"id":3031,"name":"Karur Vysya Bank"},
    {"id":3032,"name":"Kotak Mahindra Bank"},
    {"id":3033,"name":"Laxmi Vilas Bank - Retail Net Banking"},
    {"id":3037,"name":"Punjab & Sind Bank"},
    {"id":3038,"name":"Punjab National Bank - Retail Net Banking"},
    {"id":3039,"name":"RBL Bank"},
    {"id":3040,"name":"Saraswat Bank"},
    {"id":3041,"name":"Shamrao Vitthal Co-operative Bank"},
    {"id":3042,"name":"South Indian Bank"},
    {"id":3043,"name":"Standard Chartered Bank"},
    {"id":3044,"name":"State Bank Of India"},
    {"id":3051,"name":"Tamil Nadu State Co-operative Bank"},
    {"id":3052,"name":"Tamilnad Mercantile Bank Ltd"},
    {"id":3054,"name":"UCO Bank"},
    {"id":3055,"name":"Union Bank of India"},
    {"id":3058,"name":"Yes Bank Ltd"},
    {"id":3060,"name":"Bank of Baroda - Corporate"},
    {"id":3061,"name":"Bank of India - Corporate"},
    {"id":3062,"name":"DCB Bank - Corporate"},
    {"id":3064,"name":"Lakshmi Vilas Bank - Corporate"},
    {"id":3065,"name":"Punjab National Bank - Corporate"},
    {"id":3066,"name":"State Bank of India - Corporate"},
    {"id":3067,"name":"Union Bank of India - Corporate"},
    {"id":3071,"name":"Axis Bank Corporate"},
    {"id":3072,"name":"Dhanlaxmi Bank Corporate"},
    {"id":3073,"name":"ICICI Corporate Netbanking"},
    {"id":3074,"name":"Ratnakar Corporate Banking"},
    {"id":3075,"name":"Shamrao Vithal Bank Corporate"},
    {"id":3076,"name":"Equitas Small Finance Bank"},
    {"id":3077,"name":"Yes Bank Corporate"},
    {"id":3079,"name":"Bandhan Bank- Corporate banking"},
    {"id":3080,"name":"Barclays Corporate- Corporate Banking - Corporate"},
    {"id":3081,"name":"Indian Overseas Bank Corporate"},
    {"id":3083,"name":"City Union Bank of Corporate"},
    {"id":3084,"name":"HDFC Corporate"},
    {"id":3086,"name":"Shivalik Bank"},
    {"id":3087,"name":"AU Small Finance"},
    {"id":3088,"name":"Bandhan Bank - Retail Net Banking"},
    {"id":3089,"name":"Utkarsh Small Finance Bank"},
    {"id":3090,"name":"The Surat People’s Co-operative Bank Limited"},
    {"id":3091,"name":"Gujarat State Co-operative Bank Limited"},
    {"id":3092,"name":"HSBC Retail Netbanking"},
    {"id":3094,"name":"Andhra Pragathi Grameena Bank"},
    {"id":3096,"name":"Bassien Catholic Coop Bank"},
    {"id":3098,"name":"Capital Small Finance Bank"},
    {"id":3100,"name":"ESAF Small Finance Bank"},
    {"id":3101,"name":"Fincare Bank"},
    {"id":3102,"name":"Jana Small Finance Bank"},
    {"id":3103,"name":"Jio Payments Bank"},
    {"id":3104,"name":"Janata Sahakari Bank Ltd Pune"},
    {"id":3105,"name":"Kalyan Janata Sahakari Bank"},
    {"id":3106,"name":"The Kalupur Commercial Co-Operative Bank"},
    {"id":3107,"name":"Karnataka Vikas Grameena Bank"},
    {"id":3108,"name":"Maharashtra Gramin Bank"},
    {"id":3110,"name":"North East Small Finance Bank Ltd"},
    {"id":3111,"name":"NKGSB Co-op Bank"},
    {"id":3113,"name":"Karnataka Gramin Bank"},
    {"id":3114,"name":"RBL Bank Limited - Corporate Banking"},
    {"id":3115,"name":"SBM Bank India"},
    {"id":3116,"name":"Suryoday Small Finance Bank"},
    {"id":3117,"name":"The Sutex Co-op Bank Ltd"},
    {"id":3118,"name":"Thane Bharat Sahakari Bank Ltd"},
    {"id":3119,"name":"TJSB Bank"},
    {"id":3120,"name":"Varachha Co-operative Bank Limited"},
    {"id":3121,"name":"Zoroastrian Co-Operative Bank Ltd"},
    {"id":3122,"name":"UCO Bank Corporate"},
    {"id":3123,"name":"Airtel Payments Bank"}
]